README
setup.cfg
setup.py
bioinformagic_messages/__init__.py
bioinformagic_messages/bioinformagic_messages.py
bioinformagic_messages.egg-info/PKG-INFO
bioinformagic_messages.egg-info/SOURCES.txt
bioinformagic_messages.egg-info/dependency_links.txt
bioinformagic_messages.egg-info/top_level.txt